molaguttal/__init__.py
molaguttal/functions.py
molaguttal/greet.py
molaguttal-0.1.0.dist-info/METADATA
molaguttal-0.1.0.dist-info/WHEEL
molaguttal-0.1.0.dist-info/top_level.txt
molaguttal-0.1.0.dist-info/RECORD
